tiktokautouploader/__init__.py
tiktokautouploader/function.py
tiktokautouploader/Js_assets/login.js
tiktokautouploader/Js_assets/package.json
tiktokautouploader-4.5.dist-info/METADATA
tiktokautouploader-4.5.dist-info/WHEEL
tiktokautouploader-4.5.dist-info/RECORD
