Metadata-Version: 2.4
Name: tiktokautouploader
Version: 4.5
Summary: Upload or schedule videos to TikTok with viral TikTok sounds and hashtags.
Project-URL: Homepage, https://github.com/haziq-exe/TikTokAutoUploader
Author-email: HAZIQ <haziqmk123@gmail.com>
Keywords: autoupload,tiktok,tiktokautoupload
Classifier: License :: OSI Approved :: MIT License
Classifier: Operating System :: OS Independent
Classifier: Programming Language :: Python :: 3
Classifier: Programming Language :: Python :: 3.8
Classifier: Programming Language :: Python :: 3.9
Classifier: Programming Language :: Python :: 3.10
Classifier: Programming Language :: Python :: 3.11
Requires-Dist: inference>=0.18.1
Requires-Dist: pillow>=8.0.0
Requires-Dist: playwright>=1.0.0
Requires-Dist: requests>=2.0.0
Requires-Dist: scikit-learn>=0.24.0
